edgegap_cli/__init__.py
edgegap_cli/core/__init__.py
edgegap_cli/core/builders/__init__.py
edgegap_cli/core/builders/_interface.py
edgegap_cli/core/builders/_menu.py
edgegap_cli/core/builders/_terminal.py
edgegap_cli/core/handlers/__init__.py
edgegap_cli/core/handlers/_cli.py
edgegap_cli/core/handlers/_depends.py
edgegap_cli/core/handlers/_namespace.py
edgegap_cli/core/handlers/_view.py
edgegap_cli/core/models/__init__.py
edgegap_cli/core/models/_cli.py
edgegap_cli/core/models/_constraint.py
edgegap_cli/core/models/_namespace.py
edgegap_cli/core/models/_view.py
edgegap_cli/features/__init__.py
edgegap_cli/features/db/__init__.py
edgegap_cli/features/db/_config.py
edgegap_cli/features/db/_namespace.py
edgegap_cli/features/db/actions/__init__.py
edgegap_cli/features/db/actions/_current.py
edgegap_cli/features/db/actions/_downgrade.py
edgegap_cli/features/db/actions/_history.py
edgegap_cli/features/db/actions/_initialize.py
edgegap_cli/features/db/actions/_migrate.py
edgegap_cli/features/db/actions/_upgrade.py
edgegap_cli/features/db/actions/seeder/__init__.py
edgegap_cli/features/db/actions/seeder/_enum.py
edgegap_cli/features/db/actions/seeder/_handler.py
edgegap_cli/features/db/actions/seeder/_loader.py
edgegap_cli/features/db/actions/seeder/_models.py
edgegap_cli/features/db/actions/seeder/_operator.py
edgegap_cli/features/db/actions/seeder/_seeder.py
edgegap_cli/main.py
edgegap_cli-1.10.13.dist-info/LICENSE
edgegap_cli-1.10.13.dist-info/METADATA
edgegap_cli-1.10.13.dist-info/WHEEL
edgegap_cli-1.10.13.dist-info/entry_points.txt
edgegap_cli-1.10.13.dist-info/RECORD
