Metadata-Version: 2.1
Name: edgegap-cli
Version: 1.10.13
Summary: The Edgegap CLI for operations like migrations. It is designed for use within the Edgegap organization.
Author: Bastien Roy
Author-email: bastien@edgegap.com
Requires-Python: >=3.10,<4.0
Classifier: Programming Language :: Python :: 3
Classifier: Programming Language :: Python :: 3.10
Classifier: Programming Language :: Python :: 3.11
Classifier: Programming Language :: Python :: 3.12
Requires-Dist: alembic (>=1.13.1,<2.0.0)
Requires-Dist: click (>=8.1.7,<9.0.0)
Requires-Dist: console-menu (>=0.8.0,<0.9.0)
Requires-Dist: edgegap-database (>=1.6.5,<2.0.0)
Requires-Dist: edgegap-logging (>=1.2.0,<2.0.0)
Requires-Dist: edgegap-settings (>=1.6.2,<2.0.0)
Requires-Dist: sqlalchemy (>=2.0.29,<3.0.0)
Requires-Dist: textual (>=0.58.1,<0.59.0)
